elang/__init__.py
elang/version.py
elang/plot/utils/__init__.py
elang/plot/utils/embedding.py
elang/word2vec/builder/__init__.py
elang/word2vec/builder/build_wiki.py
elang/word2vec/model/demo2d.model
elang/word2vec/model/demo500d.model
elang/word2vec/utils/__init__.py
elang/word2vec/utils/cleansing.py
elang/word2vec/utils/negative/calendar-words.txt
elang/word2vec/utils/negative/indonesian-region.txt
elang/word2vec/utils/negative/stopwords-id.txt
elang/word2vec/utils/negative/swear-words.txt
elang-0.1.1.dist-info/LICENSE
elang-0.1.1.dist-info/METADATA
elang-0.1.1.dist-info/WHEEL
elang-0.1.1.dist-info/top_level.txt
elang-0.1.1.dist-info/RECORD
