Metadata-Version: 2.1
Name: elang
Version: 0.1.1
Summary: Word Embedding(E) utilities for Language(Lang) Models
Home-page: https://github.com/onlyphantom/elang
Author: Samuel Chan, Tomy Tjandra
Author-email: samuel@algorit.ma
License: UNKNOWN
Keywords: nlp bahasa indonesia indonesian natural language corpus word2vec gensim embedding nltk
Platform: UNKNOWN
Classifier: Programming Language :: Python :: 3
Classifier: License :: CC0 1.0 Universal (CC0 1.0) Public Domain Dedication
Classifier: Operating System :: OS Independent
Requires-Python: >=3.6
Requires-Dist: gensim
Requires-Dist: scikit-learn
Requires-Dist: matplotlib
Requires-Dist: tqdm
Requires-Dist: beautifulsoup4
